{
    "dbName": "Vasutechs-ERP",
    "tables": {
        "partMaster": {
            "name": "partMaster",
            "fields": {
                "id": "",
                "partNo": "",
                "partName": "",
                "rawMaterial": "",
                "inputWeight": "",
                "finishedWeight": "",
                "hsnCode": "",
                "uom": "",
                "prodRateHr": "",
                "rate": "",
                "gst": "",
                "sgst": "",
                "cgst": ""
            },
            "data": [
                {
                    "partNo": "4” SWR",
                    "partName": "SWR Clamp",
                    "rawMaterial": 1,
                    "inputWeight": 0.1,
                    "finishedWeight": 0.1,
                    "hsnCode": "1",
                    "uom": 1,
                    "prodRateHr": 100,
                    "rate": 13,
                    "gst": 18,
                    "sgst": 9,
                    "cgst": 9,
                    "id": 1
                },
                {
                    "partNo": "TestPartNo",
                    "partName": "TestPartName",
                    "rawMaterial": 1,
                    "inputWeight": 1,
                    "finishedWeight": 1,
                    "hsnCode": "1",
                    "uom": 1,
                    "prodRateHr": 1,
                    "rate": 1,
                    "gst": 2,
                    "sgst": 1,
                    "cgst": 1,
                    "id": 2
                }
            ]
        },
        "customerMaster": {
            "name": "customerMaster",
            "fields": {
                "customerCode": "",
                "customerName": "",
                "address": "",
                "contactNo": "",
                "gstin": "",
                "mapping": [
                    {
                        "id": "",
                        "partName": "",
                        "rate": "",
                        "gst": ""
                    }
                ]
            },
            "data": [
                {
                    "customerCode": 1,
                    "customerName": "Guhan Electricals",
                    "address": "Myl",
                    "contactNo": 123123,
                    "gstin": 23123123,
                    "mapping": [
                        {
                            "id": 1,
                            "partName": "SWR Clamp",
                            "rate": 13,
                            "gst": 18
                        }
                    ],
                    "id": 1
                }
            ]
        },
        "empMaster": {
            "name": "empMaster",
            "fields": {
                "id": "",
                "employeeCode": "",
                "employeeName": "",
                "address": "",
                "contactNo": "",
                "mailId": "",
                "qualification": "",
                "designation": "",
                "basicSalary": "",
                "hra": "",
                "ca": "",
                "ot": "",
                "totalSalary": ""
            },
            "data": [
                {
                    "id": 1,
                    "employeeCode": 1,
                    "employeeName": "Sugadevan",
                    "address": "myl",
                    "contactNo": 121212,
                    "mailId": "test@test.com",
                    "qualification": "ME",
                    "designation": "Manager",
                    "basicSalary": 9000,
                    "hra": 0,
                    "ca": 0,
                    "ot": 0,
                    "totalSalary": "",
                    "total": 9000
                }
            ]
        },
        "uomMaster": {
            "name": "uomMaster",
            "fields": {
                "id": "",
                "uomCode": "",
                "uomName": ""
            },
            "data": [
                {
                    "uomCode": "1",
                    "uomName": "KG",
                    "id": 1
                }
            ]
        },
        "invoice": {
            "name": "uomMaster",
            "fields": {
                "id": "",
                "invoiceNo": "",
                "date": "",
                "customerCode": "",
                "partyGstin": "",
                "partyArnNo": "",
                "taxRate": "",
                "cgst": "",
                "sgst": "",
                "total": "",
                "details": {
                    "sNo": "",
                    "partNo": "",
                    "unit": "",
                    "rate": "",
                    "amount": ""
                }
            },
            "data": [
                {
                    "invoiceNo": "1/2018",
                    "date": "",
                    "customerCode": "1",
                    "partyGstin": "",
                    "partyArnNo": "",
                    "taxRate": "",
                    "cgst": "",
                    "sgst": "",
                    "total": "",
                    "mapping": [
                        {
                            "id": 1,
                            "sNo": "",
                            "partNo": "",
                            "partName": "",
                            "unit": "",
                            "rate": "",
                            "amount": ""
                        }
                    ],
                    "id": 1
                }
            ]
        },
        "rmMaster": {
            "name": "rmMaster",
            "fields": {
                "id": "",
                "rmCode": "",
                "rmName": "",
                "grade": "",
                "type": "",
                "hsnCode": "",
                "uom": "",
                "rate": "",
                "gst": "",
                "sgst": "",
                "cgst": ""
            },
            "data": [
                {
                    "rmCode": 1,
                    "rmName": "2 x 16 MS – HR Coil",
                    "grade": "MS",
                    "type": "HR Coil",
                    "hsnCode": "1",
                    "uom": 1,
                    "rate": 1,
                    "gst": 18,
                    "sgst": 9,
                    "cgst": 9,
                    "id": 1
                }
            ]
        },
        "supplierMaster": {
            "name": "supplierMaster",
            "fields": {
                "supplierCode": "",
                "supplierName": "",
                "address": "",
                "contactNo": "",
                "gstin": "",
                "mapping": [
                    {
                        "id": "",
                        "rmCode": "",
                        "rmName": "",
                        "rate": "",
                        "gst": ""
                    }
                ]
            },
            "data": [
                {
                    "supplierCode": 1,
                    "supplierName": "Kamal Steel Corportaion",
                    "address": "Chennai",
                    "contactNo": 213123,
                    "gstin": 13123123,
                    "mapping": [
                        {
                            "id": 1,
                            "rmCode": 1,
                            "rmName": "2 x 16 MS – HR Coil",
                            "rate": 10,
                            "gst": 18
                        }
                    ],
                    "id": 1
                }
            ]
        },
        "poSupplier": {
            "name": "poSupplier",
            "fields": {
                "poNo": "",
                "date": "",
                "supplierCode": "",
                "gstin": "",
                "mapping": [
                    {
                        "id": "",
                        "rmName": "",
                        "qty": "",
                        "uom": "",
                        "rate": "",
                        "gst": "",
                        "cgst": "",
                        "sgst": "",
                        "total": ""
                    }
                ]
            },
            "data": [
                {
                    "poNo": 1,
                    "date": "2018-05-11T04:00:00.000Z",
                    "supplierCode": 1,
                    "mapping": [
                        {
                            "id": 1,
                            "rmName": "2 x 16 MS – HR Coil",
                            "qty": "5",
                            "uom": 1,
                            "rate": 10,
                            "gst": 18,
                            "cgst": 9,
                            "sgst": 9,
                            "total": "68.00"
                        }
                    ],
                    "id": 1,
                    "gstin": 13123123
                }
            ]
        },
        "subContractorMaster": {
            "name": "subContractorMaster",
            "fields": {
                "subContractorCode": "",
                "subContractorName": "",
                "address": "",
                "contactNo": "",
                "gstin": "",
                "mapping": [
                    {
                        "id": "",
                        "partName": "",
                        "oppCode": "",
                        "rate": "",
                        "gst": ""
                    }
                ]
            },
            "data": [
                {
                    "subContractorCode": 1,
                    "subContractorName": "Test Sub Contractor",
                    "address": "szdasd",
                    "contactNo": 21312,
                    "gstin": 324234,
                    "mapping": [
                        {
                            "id": 1,
                            "partName": "SWR Clamp",
                            "oppCode": "",
                            "rate": "1",
                            "gst": "1"
                        }
                    ],
                    "id": 1
                }
            ]
        },
        "poSubContractor": {
            "name": "poSubContractor",
            "fields": {
                "poNo": "",
                "date": "",
                "subContractorCode": "",
                "gstin": "",
                "mapping": [
                    {
                        "id": "",
                        "partName": "",
                        "oppCode": "",
                        "qty": "",
                        "uom": "",
                        "rate": "",
                        "gst": "",
                        "cgst": "",
                        "sgst": "",
                        "total": ""
                    }
                ]
            },
            "data": [
                {
                    "poNo": 1,
                    "date": "2018-05-06T04:00:00.000Z",
                    "subContractorCode": 1,
                    "gstin": 324234,
                    "mapping": [
                        {
                            "id": 1,
                            "partName": "SWR Clamp",
                            "oppCode": "",
                            "qty": "1",
                            "uom": "1",
                            "rate": 13,
                            "gst": 18,
                            "cgst": 9,
                            "sgst": 9,
                            "total": "17.68"
                        }
                    ],
                    "supplierCode": "1",
                    "id": 1
                }
            ]
        },
        "grnSupplier": {
            "name": "grnSupplier",
            "fields": {
                "grnNo": "",
                "date": "",
                "supplierCode": "",
                "supplierDCNo": "",
                "supplierDCDate": "",
                "mapping": [
                    {
                        "id": "",
                        "rmCode": "",
                        "rmName": "",
                        "poQty": "",
                        "uom": "",
                        "receivedQty": "",
                        "acceptedQty": "",
                        "rate": "",
                        "gst": "",
                        "cost": "",
                        "total": ""
                    }
                ]
            },
            "data": [
                {
                    "grnNo": 1,
                    "date": "2018-05-06T04:00:00.000Z",
                    "supplierCode": "",
                    "supplierDCNo": "",
                    "supplierDCDate": "2018-05-01T04:00:00.000Z",
                    "mapping": [
                        {
                            "id": "",
                            "rmCode": "",
                            "rmName": "",
                            "poQty": "",
                            "uom": "",
                            "receivedQty": "",
                            "acceptedQty": "",
                            "rate": "",
                            "gst": "",
                            "cost": "",
                            "total": ""
                        }
                    ],
                    "supplierDCCode": "1",
                    "id": 1
                }
            ]
        },
        "dcSupplier": {
            "name": "dcSupplier",
            "fields": {
                "dcNo": "",
                "date": "",
                "supplierCode": "",
                "mapping": [
                    {
                        "id": "",
                        "rmCode": "",
                        "rmName": "",
                        "poQty": "",
                        "total": ""
                    }
                ]
            },
            "data": [
                {
                    "dcNo": 1,
                    "date": "2018-05-07T04:00:00.000Z",
                    "supplierCode": "",
                    "mapping": [
                        {
                            "id": "",
                            "rmCode": "",
                            "rmName": "",
                            "poQty": "",
                            "total": ""
                        }
                    ],
                    "id": 1
                }
            ]
        },
        "grnSubContractor": {
            "name": "grnSubContractor",
            "fields": {
                "grnNo": "",
                "date": "",
                "subContractorCode": "",
                "subContractorDCNo": "",
                "subContractorDCDate": "",
                "mapping": [
                    {
                        "id": "",
                        "partNo": "",
                        "partName": "",
                        "partFrom": "",
                        "ourDCNo": "",
                        "dcQty": "",
                        "uom": "",
                        "receivedQty": "",
                        "acceptedQty": "",
                        "rate": "",
                        "gst": "",
                        "cost": "",
                        "total": ""
                    }
                ]
            },
            "data": []
        },
        "dcSubContractor": {
            "name": "dcSubContractor",
            "fields": {
                "dcNo": "",
                "date": "",
                "subContractorCode": "",
                "mapping": [
                    {
                        "id": "",
                        "partNo": "",
                        "partFrom": "",
                        "forPurpose": "",
                        "qty": "",
                        "uom": "",
                        "appCost": ""
                    }
                ]
            },
            "data": []
        },
        "operationMaster": {
            "name": "operationMaster",
            "fields": {
                "opNo": "",
                "opName": "",
                "source": ""
            },
            "data": [
                {
                    "opNo": "10",
                    "opName": "Raw Material",
                    "source": "Supplier",
                    "id": 1
                }
            ]
        },
        "bom": {
            "name": "bom",
            "fields": {
                "partNo": "",
                "rmCode": "",
                "partNorms": ""
            },
            "data": [
                {
                    "partNo": "4” SWR",
                    "rmCode": 1,
                    "partNorms": "0.1",
                    "id": 1
                }
            ]
        },
        "machineMaster": {
            "name": "machineMaster",
            "fields": {
                "machineNo": "",
                "machineName": "",
                "make": "",
                "model": "",
                "capacity": "",
                "yoe": "",
                "value": ""
            },
            "data": [
                {
                    "machineNo": 1,
                    "machineName": "Hydro pneumatic Press",
                    "make": "Britt",
                    "model": "xxxx",
                    "capacity": "15 Ton",
                    "yoe": "2017",
                    "value": "131000",
                    "id": 1
                }
            ]
        },
        "flowMaster": {
            "name": "flowMaster",
            "fields": {
                "partNo": "",
                "partName": "",
                "mapping": [
                    {
                        "id": "",
                        "opName": "",
                        "source": ""
                    }
                ]
            },
            "data": [
                {
                    "partNo": "4” SWR",
                    "mapping": [
                        {
                            "id": 1,
                            "opName": "Raw Material",
                            "source": "Supplier"
                        }
                    ],
                    "id": 1
                }
            ]
        },
        "toolMaster": {
            "name": "toolMaster",
            "fields": {
                "toolNo": "",
                "partName": "",
                "make": "",
                "type": "",
                "toolLife": "",
                "yoe": "",
                "value": ""
            },
            "data": [
                {
                    "toolNo": 1,
                    "partName": "Cropping Tool",
                    "make": "Crescent",
                    "type": "Pillar set",
                    "toolLife": "100000",
                    "yoe": "2005",
                    "value": "15000",
                    "id": 1,
                    "yop": "2015"
                }
            ]
        },
        "materialIssueNote": {
            "name": "materialIssueNote",
            "fields": {
                "jobCardNo": "",
                "date": "",
                "rmCode": "",
                "partNo": "",
                "norms": "",
                "issueQty": "",
                "qtyCanMake": "",
                "issueStage": ""
            },
            "data": [
                {
                    "jobCardNo": 1,
                    "date": "2018-05-21T01:22:16.640Z",
                    "rmCode": 1,
                    "partNo": 1,
                    "norms": "1",
                    "issueQty": "1",
                    "qtyCanMake": "1",
                    "issueStage": "1",
                    "id": 1
                }
            ]
        },
        "productionEntry": {
            "name": "productionEntry",
            "fields": {
                "date": "",
                "mcNo": "",
                "jobCardNo": "",
                "partNo": "",
                "operationFrom": "",
                "operationTo": "",
                "toolNo": "",
                "operator": "",
                "startTime": "",
                "endTime": "",
                "planQty": "",
                "acceptedQty": "",
                "rejectionQty": "",
                "rmQty": ""
            },
            "data": [
                {
                    "date": "2018-05-21T02:47:36.837Z",
                    "mcNo": 1,
                    "jobCardNo": 1,
                    "partNo": 1,
                    "operationFrom": 1,
                    "operationTo": 1,
                    "toolNo": 1,
                    "operator": null,
                    "startTime": "2018-05-20T04:00:00.000Z",
                    "endTime": "2018-05-27T04:00:00.000Z",
                    "planQty": "1",
                    "acceptedQty": "1",
                    "rejectionQty": "0",
                    "rmQty": "0",
                    "Operator": 1,
                    "id": 1
                }
            ]
        }
    }
}